uniblock/Blocks.txt
uniblock/__init__.py
uniblock/uniblock.py
uniblock-1.0.4.dist-info/LICENSE
uniblock-1.0.4.dist-info/METADATA
uniblock-1.0.4.dist-info/WHEEL
uniblock-1.0.4.dist-info/entry_points.txt
uniblock-1.0.4.dist-info/top_level.txt
uniblock-1.0.4.dist-info/RECORD
